{
    "modacGPIOConfig": "[{\"Pin\": \"1\", \"GPIO\": \"V3.3\", \"MODAC\": \"V3.3\", \"WaveShareUse\": \"3.3V\"}, {\"Pin\": \"2\", \"GPIO\": \"V5\", \"MODAC\": \"V5\", \"WaveShareUse\": \"5V\"}, {\"Pin\": \"3\", \"GPIO\": \"2\", \"MODAC\": \"I2C SDA\", \"WaveShareUse\": \"nc\"}, {\"Pin\": \"4\", \"GPIO\": \"V5\", \"MODAC\": \"V5\", \"WaveShareUse\": \"5V\"}, {\"Pin\": \"5\", \"GPIO\": \"3\", \"MODAC\": \"I2C SCL\", \"WaveShareUse\": \"nc\"}, {\"Pin\": \"6\", \"GPIO\": \"gnd\", \"MODAC\": \"gnd\", \"WaveShareUse\": \"GND\"}, {\"Pin\": \"7\", \"GPIO\": \"4\", \"MODAC\": \"oled reset\", \"WaveShareUse\": \"nc\"}, {\"Pin\": \"8\", \"GPIO\": \"14\", \"MODAC\": \"Serial TXD\", \"WaveShareUse\": \"nc\"}, {\"Pin\": \"9\", \"GPIO\": \"gnd\", \"MODAC\": \"gnd\", \"WaveShareUse\": \"GND\"}, {\"Pin\": \"10\", \"GPIO\": \"15\", \"MODAC\": \"Serial RXD\", \"WaveShareUse\": \"nc\"}, {\"Pin\": \"11\", \"GPIO\": \"17\", \"MODAC\": \"w\", \"WaveShareUse\": \"DRDY ADS1256 data ready, active low\"}, {\"Pin\": \"12\", \"GPIO\": \"18\", \"MODAC\": \"w\", \"WaveShareUse\": \"RESET ADS1256 reset input\"}, {\"Pin\": \"13\", \"GPIO\": \"27\", \"MODAC\": \"w\", \"WaveShareUse\": \"PDWN ADS1256 sync/power off input, low active\"}, {\"Pin\": \"14\", \"GPIO\": \"gnd\", \"MODAC\": \"gnd\", \"WaveShareUse\": \"GND\"}, {\"Pin\": \"15\", \"GPIO\": \"22\", \"MODAC\": \"w\", \"WaveShareUse\": \"CS0 ADS1256 chip select, low active\"}, {\"Pin\": \"16\", \"GPIO\": \"23\", \"MODAC\": \"w\", \"WaveShareUse\": \"CS1 DAC8532 chip select, low active\"}, {\"Pin\": \"17\", \"GPIO\": \"V3.3\", \"MODAC\": \"V3.3\", \"WaveShareUse\": \"3.3V\"}, {\"Pin\": \"18\", \"GPIO\": \"24\", \"MODAC\": \"Relay_8\", \"WaveShareUse\": \"nc\"}, {\"Pin\": \"19\", \"GPIO\": \"10\", \"MODAC\": \"w\", \"WaveShareUse\": \"DIN SPI data input\"}, {\"Pin\": \"20\", \"GPIO\": \"gnd\", \"MODAC\": \"gnd\", \"WaveShareUse\": \"GND\"}, {\"Pin\": \"21\", \"GPIO\": \"9\", \"MODAC\": \"w\", \"WaveShareUse\": \"DOUT SPI data output\"}, {\"Pin\": \"22\", \"GPIO\": \"25\", \"MODAC\": \"Relay_7\", \"WaveShareUse\": \"nc\"}, {\"Pin\": \"23\", \"GPIO\": \"11\", \"MODAC\": \"w\", \"WaveShareUse\": \"SCK SPI clock\"}, {\"Pin\": \"24\", \"GPIO\": \"8\", \"MODAC\": \"Relay_6\", \"WaveShareUse\": \"\"}, {\"Pin\": \"25\", \"GPIO\": \"gnd\", \"MODAC\": \"gnd\", \"WaveShareUse\": \"GND\"}, {\"Pin\": \"26\", \"GPIO\": \"7\", \"MODAC\": \"Relay_5\", \"WaveShareUse\": \"\"}, {\"Pin\": \"27\", \"GPIO\": \"id_sc1\", \"MODAC\": \"id sc\", \"WaveShareUse\": \"id sc\"}, {\"Pin\": \"28\", \"GPIO\": \"id_sc2\", \"MODAC\": \"id sc\", \"WaveShareUse\": \"id sc\"}, {\"Pin\": \"29\", \"GPIO\": \"5\", \"MODAC\": \"Relay_0 outlet\", \"WaveShareUse\": \"nc\"}, {\"Pin\": \"30\", \"GPIO\": \"gnd\", \"MODAC\": \"\", \"WaveShareUse\": \"GND\"}, {\"Pin\": \"31\", \"GPIO\": \"6\", \"MODAC\": \"\", \"WaveShareUse\": \"Sensor - D0\"}, {\"Pin\": \"32\", \"GPIO\": \"12\", \"MODAC\": \"Relay_4\", \"WaveShareUse\": \"nc\"}, {\"Pin\": \"33\", \"GPIO\": \"13\", \"MODAC\": \"\", \"WaveShareUse\": \"Sensor - D1\"}, {\"Pin\": \"34\", \"GPIO\": \"gnd\", \"MODAC\": \"\", \"WaveShareUse\": \"GND\"}, {\"Pin\": \"35\", \"GPIO\": \"19\", \"MODAC\": \"\", \"WaveShareUse\": \"sensor \\u2013 D2\"}, {\"Pin\": \"36\", \"GPIO\": \"16\", \"MODAC\": \"Relay_3\", \"WaveShareUse\": \"nc\"}, {\"Pin\": \"37\", \"GPIO\": \"26\", \"MODAC\": \"\", \"WaveShareUse\": \"sensor \\u2013 D3\"}, {\"Pin\": \"38\", \"GPIO\": \"20\", \"MODAC\": \"Relay_2\", \"WaveShareUse\": \"nc\"}, {\"Pin\": \"39\", \"GPIO\": \"gnd\", \"MODAC\": \"gnd\", \"WaveShareUse\": \"GND\"}, {\"Pin\": \"40\", \"GPIO\": \"21\", \"MODAC\": \"Relay_1\", \"WaveShareUse\": \"nc\"}]"
}